Metadata-Version: 1.1
Name: fossilpy
Version: 0.2
Summary: Simple pure-python library for reading Fossil repositories.
Home-page: https://github.com/gumblex/fossilpy
Author: Dingyuan Wang
Author-email: gumblex@aosc.io
License: BSD
Keywords: fossil
Platform: any
Classifier: Development Status :: 3 - Alpha
Classifier: Intended Audience :: Developers
Classifier: License :: OSI Approved :: BSD License
Classifier: Topic :: Software Development :: Version Control
Classifier: Programming Language :: Python :: 3
Classifier: Programming Language :: Python :: 3 :: Only
